{
  "basics": {
    "name": "Ricardo Figueroa Quiroga",
    "label": "Java Developer",
    "picture": "",
    "email": "rfigueroaoficial@gmail.com",
    "phone": "3317008650",
    "website": "https://rfigueroa.github.io",
    "summary": "I was born in Tamaulipas Mexico, Currently work at Unosquare as a Senior Java Engineer, Before working at Unosquare I was a Senior Java Developer at EcareSoft. While my work focuses on the back end, I also have working experience on the front end using Angular, JQuery and vanilla javascript. While his work focuses on applied information theory, mostly optimizing lossless compression schema of both the length-limited and adaptive variants, ",
    "location": {
      "address": "Privada Azucena #137, Foret Residencial, El Fortin",
      "postalCode": "45066",
      "city": "Zapopan",
      "countryCode": "MX",
      "region": "Jalisco"
    },
    "profiles": [
      {
        "network": "Twitter",
        "username": "rfqOficial",
        "url": ""
      },
      {
        "network": "Github",
        "username": "rfigueroa",
        "url": ""
      }
    ]
  },
  "work": [
    {
      "company": "Unosquare",
      "position": "Senior Java Engineer",
      "website": "https://unosquare.com",
      "startDate": "2013-03-01",
      "endDate": "",
      "summary": "At Unosquare I work as a Senior Java Engineer, I been involved in several projects ranging from legacy java applications to creating node js apps from scratch",
      "highlights": [
        "Added support for a questions & answers section on an e-commerce site using a third party API",
        "Added versioning support for one of the resources provided on the API allowing users to access different version dependig at what point in time the bought the item",
        "Worked on several projects doing Tier 2 and Tier 3 support"
      ]
    },
    {
      "company": "Ecaresoft",
      "position": "Senior Java Develoeper",
      "website": "http://www.ecaresoft.com/",
      "startDate": "2007-04-01",
      "endDate": "2012-12-01",
      "summary": "At Ecaresoft I worked as a Senior Java Developer on some of the product the company produces, ranging for a CRM/ERM, Payroll System and HIS software ",
      "highlights": [
        "Added support to allow each hospital to customized the content of sent and received HL7 messages",
        "Designed, developed and implemented the functionality to reach Suresctipts certification for electronic prescribing",
        "Developed the printing jobs for the checks generated by the payroll system of the Tamaulipas Department of Educations"
      ]
    }
  ],
  "volunteer": [],
  "education": [
    {
      "institution": "Universidad Autonoma de Tamaulipas",
      "area": "Ingeniero en Telematica",
      "studyType": "partial credits",
      "startDate": "2011-06-01",
      "endDate": "",
      "gpa": "",
      "courses": []
    }
  ],
  "awards": [],
  "publications": [],
  "skills": [
    {
      "name": "Java Development",
      "level": "",
      "keywords": [
        "Spring",
        "JPA",
        "JAXB",
        "JDBC"
      ]
    },
    {
      "name": "Web Development",
      "level": "",
      "keywords": [
        "NodeJS",
        "express",
        "Jquery"
      ]
    }
  ],
  "languages": [
    {
      "language": "English",
      "fluency": "Full professional proficiency"
    },
    {
      "language": "Spanish",
      "fluency": "Native speaker"
    }
  ],
  "interests": [
    {
      "name": "Exercise",
      "keywords": [
        "Running",
        "MTB"
      ]
    },
    {
      "name": "Sports",
      "keywords": [
        "Chivas"
      ]
    }
  ],
  "references": []
}